[
    {
        "nom": "Cuisine Italina",
        "estrelles": 4,
        "harari": "de 9 a 10",
        "fechas": "lunes y martes",
        "modalidad": "online/presencial",
        "telefon": 999000000,
        "creador": "Lourdes Monserrat",
        "descripció": "La millor cuina del món",
        "web": "www.supermercatveggie.cat",
        "fotos": "assets/img/close-icon.svg",
        "mapa": "assets/img/close-icon.svg",
        "opiniones": {
            "1 estrella": {},
            "2 estrellas": {},
            "3 estrellas":{},
            "4 estrellas": {},
            "5 estrellas": {}
        },
        "opciones": "veganas, vegetarianas, sin gluten"
        
    }
]